ModelCatalogue/ModelCatalogue.py
ModelCatalogue/__init__.py
ModelCatalogue/constants.py
ModelCatalogue-1.0.2.dist-info/METADATA
ModelCatalogue-1.0.2.dist-info/WHEEL
ModelCatalogue-1.0.2.dist-info/top_level.txt
ModelCatalogue-1.0.2.dist-info/RECORD
